{
  "editor.multiCursorModifier": "alt",
  "editor.formatOnSave": true,
  "editor.fontFamily": "Cascadia Code",
  "editor.fontSize": 13,
  "window.zoomLevel": 0,
  "editor.tabSize": 2,
  "editor.renderIndentGuides": false,
  "editor.fontLigatures": true,
  "explorer.confirmDragAndDrop": false,
  "explorer.confirmDelete": false,
  "git.enableSmartCommit": true,
  "git.autofetch": true,
  "workbench.editor.enablePreviewFromQuickOpen": false,
  "files.insertFinalNewline": true,
  "files.trimFinalNewlines": true,
  "editor.minimap.renderCharacters": false,
  "editor.minimap.enabled": false,
  "editor.acceptSuggestionOnEnter": "off",
  "window.nativeFullScreen": false,
  "workbench.startupEditor": "newUntitledFile",
  "breadcrumbs.enabled": true,
  "eslint.packageManager": "yarn",
  "eslint.workingDirectories": [
    { "directory": "./services/frontend", "changeProcessCWD": true },
    {
      "directory": "./services/graphql-app",
      "changeProcessCWD": true
    }
  ],
  "typescript.updateImportsOnFileMove.enabled": "always",
  "terminal.integrated.shellArgs.osx": [],
  "javascript.updateImportsOnFileMove.enabled": "always",
  "diffEditor.renderSideBySide": true,
  "terminal.integrated.rendererType": "dom",
  "reason_language_server.per_value_codelens": true,
  "workbench.colorTheme": "Atom One Dark",
  "reason_language_server.autoRebuild": false,
  "[javascript]": {
    "editor.defaultFormatter": "esbenp.prettier-vscode"
  },
  "[typescript]": {
    "editor.defaultFormatter": "esbenp.prettier-vscode"
  },
  "[json]": {
    "editor.defaultFormatter": "esbenp.prettier-vscode"
  },
  "extensions.ignoreRecommendations": false
}
